stocksdashboard/__init__.py
stocksdashboard/config.ini
stocksdashboard/dashboard_with_widgets.py
stocksdashboard/formatter.py
stocksdashboard/main.py
stocksdashboard/setup.py
stocksdashboard/stocksdashboard.py
stocksdashboard-0.40.dev0.dist-info/DESCRIPTION.rst
stocksdashboard-0.40.dev0.dist-info/METADATA
stocksdashboard-0.40.dev0.dist-info/RECORD
stocksdashboard-0.40.dev0.dist-info/WHEEL
stocksdashboard-0.40.dev0.dist-info/metadata.json
stocksdashboard-0.40.dev0.dist-info/top_level.txt
